cmdexy/__init__.py
cmdexy/cli/__init__.py
cmdexy/cli/interactive.py
cmdexy/cli/run.py
cmdexy/cli/wrapper.py
cmdexy/core/__init__.py
cmdexy/core/ai_engine.py
cmdexy/core/config.py
cmdexy/core/controller.py
cmdexy/core/execution.py
cmdexy/main.py
cmdexy-1.0.0.dist-info/METADATA
cmdexy-1.0.0.dist-info/WHEEL
cmdexy-1.0.0.dist-info/entry_points.txt
cmdexy-1.0.0.dist-info/licenses/LICENSE
cmdexy-1.0.0.dist-info/RECORD
