Metadata-Version: 2.4
Name: cmdexy
Version: 1.0.0
Summary: AI-powered CLI assistant with automatic error recovery and code fixing.
License: MIT
License-File: LICENSE
Keywords: cli,ai,assistant,error-recovery,cohere,automation
Author: Akhilesh S
Author-email: akhilesh2220@github.com
Requires-Python: >=3.10,<4.0
Classifier: Development Status :: 4 - Beta
Classifier: Environment :: Console
Classifier: Intended Audience :: Developers
Classifier: License :: OSI Approved :: MIT License
Classifier: Operating System :: OS Independent
Classifier: Programming Language :: Python :: 3
Classifier: Programming Language :: Python :: 3.10
Classifier: Programming Language :: Python :: 3.11
Classifier: Programming Language :: Python :: 3.12
Classifier: Programming Language :: Python :: 3.13
Classifier: Programming Language :: Python :: 3.14
Classifier: Topic :: Software Development :: Libraries :: Python Modules
Classifier: Topic :: Utilities
Requires-Dist: cohere (>=4.0.0,<5.0.0)
Requires-Dist: docker (>=7.0.0,<8.0.0)
Requires-Dist: pydantic (>=2.0.0,<3.0.0)
Requires-Dist: python-dotenv (>=1.0.0,<2.0.0)
Requires-Dist: rich (>=13.0.0,<14.0.0)
Requires-Dist: typer[all] (>=0.21.1,<0.22.0)
Project-URL: Homepage, https://github.com/akhilesh2220/cmdexy
Project-URL: Repository, https://github.com/akhilesh2220/cmdexy
